datacleancwcy/__init__.py
datacleancwcy/helper_functions.py
datacleancwcy-0.0.0.dist-info/LICENSE
datacleancwcy-0.0.0.dist-info/METADATA
datacleancwcy-0.0.0.dist-info/WHEEL
datacleancwcy-0.0.0.dist-info/top_level.txt
datacleancwcy-0.0.0.dist-info/RECORD
