Metadata-Version: 2.1
Name: datacleancwcy
Version: 0.0.0
Summary: data clean
Home-page: https://github.com/ChristineWangcy/datacleancwcy
Author: Christine
Author-email: christine.cyan.wang@gmail.com
License: MIT
Platform: UNKNOWN
License-File: LICENSE
